LICENSE.md
README.md
pyproject.toml
camera_ui_rpc/__init__.py
camera_ui_rpc/channel.py
camera_ui_rpc/chunking.py
camera_ui_rpc/client.py
camera_ui_rpc/codec.py
camera_ui_rpc/decorators.py
camera_ui_rpc/errors.py
camera_ui_rpc/executor.py
camera_ui_rpc/handler.py
camera_ui_rpc/py.typed
camera_ui_rpc/service.py
camera_ui_rpc/svcm.py
camera_ui_rpc/types.py
camera_ui_rpc/utils.py
camera_ui_rpc.egg-info/PKG-INFO
camera_ui_rpc.egg-info/SOURCES.txt
camera_ui_rpc.egg-info/dependency_links.txt
camera_ui_rpc.egg-info/requires.txt
camera_ui_rpc.egg-info/top_level.txt